[
  {
    "id": "cu_summer_programs_2026",
    "name": "Лето в Центре - Летние программы Центрального университета",
    "description": "Лето в Центре – Проведи лето с Центральным университетом\nЛето в Центре\nЗарегистрироваться\nЛето — это время, когда нужно успеть набраться сил, получить много ярких впечатлений и узнать что-то новое. ",
    "type": "летняя программа",
    "format": "очно",
    "duration": "10-12 недель",
    "targetAudience": [
      "8 класс",
      "9 класс",
      "10 класс",
      "11 класс"
    ],
    "subjects": [
      "IT",
      "Программирование",
      "Аналитика",
      "Бизнес"
    ],
    "benefits": {
      "bvi": false,
      "points100": false,
      "additionalPoints": 0,
      "grants": "50%",
      "tuitionDiscount": null,
      "priority": false,
      "earlyAdmission": false
    },
    "relevantDirections": [
      "все направления",
      "бизнес",
      "IT"
    ],
    "dates": {
      "registration": "2026-04-01 - 2026-05-31",
      "event": "2026-06-20 - 2026-08-31"
    },
    "cost": {
      "type": "платно",
      "amount": 0
    },
    "participationRequirements": [
      "Быть школьником",
      "Зарегистрироваться на программу",
      "Пройти отбор"
    ],
    "selectionProcess": "По мотивационному письму и резюме",
    "participantLimit": 200,
    "website": "https://cu.ru/summer",
    "regulations": null
  },
  {
    "id": "t_education_stem_camp",
    "name": "STEM-сборы от Т-Образования и Центрального университета",
    "description": "STEM-сборы\nПропустить навигацию\nШкольникам\nКурсы с нуля\nОлимпиады и подготовка\nСмены в Сириусе\nБилет в лето\nПроектная деятельность\nПолезные материалы\nМероприятия\nСтудентам и начинающим\nКурсы с нуля\nС ",
    "type": "летняя программа",
    "format": "выездное",
    "duration": "1-2 недели",
    "targetAudience": [
      "7 класс",
      "8 класс",
      "9 класс",
      "10 класс"
    ],
    "subjects": [
      "Математика",
      "Физика",
      "Биология",
      "Технологии"
    ],
    "benefits": {
      "bvi": false,
      "points100": false,
      "additionalPoints": 0,
      "grants": "50%",
      "tuitionDiscount": null,
      "priority": false,
      "earlyAdmission": false
    },
    "relevantDirections": [
      "IT",
      "все направления"
    ],
    "dates": {
      "registration": "2026-03-01 - 2026-05-31",
      "event": "июль-август 2026"
    },
    "cost": {
      "type": "платно",
      "amount": 50000
    },
    "participationRequirements": [
      "Быть школьником 7-10 классов",
      "Интерес к STEM",
      "Способность к командной работе"
    ],
    "selectionProcess": "Открытый набор с возможностью конкурса",
    "participantLimit": 150,
    "website": "https://education.tbank.ru/school/events/stem-camp/",
    "regulations": null
  },
  {
    "id": "t_education_summer_intensive_physics",
    "name": "Летние интенсивы по физике от Т-Образования",
    "description": "Интенсив по физике\nПропустить навигацию\nШкольникам\nКурсы с нуля\nОлимпиады и подготовка\nСмены в Сириусе\nБилет в лето\nПроектная деятельность\nПолезные материалы\nМероприятия\nСтудентам и начинающим\nКурсы с",
    "type": "летняя программа",
    "format": "очно",
    "duration": "2-4 недели",
    "targetAudience": [
      "8 класс",
      "9 класс",
      "10 класс",
      "11 класс"
    ],
    "subjects": [
      "Физика",
      "Экспериментальная физика"
    ],
    "benefits": {
      "bvi": false,
      "points100": false,
      "additionalPoints": 3,
      "grants": null,
      "tuitionDiscount": null,
      "priority": false,
      "earlyAdmission": false
    },
    "relevantDirections": [
      "все направления"
    ],
    "dates": {
      "registration": "2026-04-01 - 2026-06-15",
      "event": "июль-август 2026"
    },
    "cost": {
      "type": "платно",
      "amount": 35000
    },
    "participationRequirements": [
      "Быть школьником",
      "Интерес к физике"
    ],
    "selectionProcess": "Открытый набор",
    "website": "https://education.tbank.ru/school/events/physics/",
    "regulations": null
  }
]