[
  {
    "id": "school_001",
    "name": "Университетская гимназия МГУ",
    "description": "Новости\n8 (985) 222-04-10\nПриемная комиссия\nпн-пт (с 10 до 18 по МСК)\nПомощь ученикам в оформлении пропуска\nУслуги\nПомощь в освоении\nУслуги\nПоможет ли психолог?\nВопрос-ответ\nПомощь ученикам в оформлен",
    "type": "школа-интернат",
    "format": "очно",
    "duration": "2-3 года (8-11 классы)",
    "targetAudience": [
      "8 класс",
      "10 класс"
    ],
    "subjects": [
      "Экономика",
      "Обществознание",
      "Математика",
      "Английский язык",
      "История",
      "Физика",
      "Литература"
    ],
    "benefits": {
      "bvi": false,
      "points100": false,
      "additionalPoints": 0,
      "grants": null,
      "tuitionDiscount": null,
      "priority": false,
      "earlyAdmission": false
    },
    "relevantDirections": [
      "экономика",
      "менеджмент"
    ],
    "dates": {
      "registration": "2026-01-15 - 2026-02-17",
      "event": "2026-02-20 - 2026-07-11",
      "final": "2026-07-11"
    },
    "cost": {
      "type": "бесплатно",
      "amount": 0
    },
    "participationRequirements": [
      "Учащиеся 7-8 классов для поступления в 8 класс",
      "Учащиеся 9-10 классов для поступления в 10 класс"
    ],
    "selectionProcess": "3-этапная приемная кампания: I этап - дистанционное тестирование по профильному предмету; II этап - очные письменные экзамены; III этап - летняя школа",
    "participantLimit": 10,
    "website": "https://school.msu.ru",
    "regulations": "https://school.msu.ru/admission/"
  },
  {
    "id": "school_002",
    "name": "Экономико-математическая школа (ЭМШ) - очное отделение",
    "description": "ЭМШ\nНапишите нам:\n[email protected]\nУчёба в 2025-2026\nРасписание 2025-2026\nСпецкурсы 2025-2026\nЗачётные курсы 2025-2026\nПоступление\nВступительные тесты прошлых лет\nКНР\nЭМШ-онлайн\nоб ЭМШ-онлайн\nНовости",
    "type": "профильные классы",
    "format": "очно",
    "duration": "2 года (10-11 классы)",
    "targetAudience": [
      "10 класс",
      "11 класс"
    ],
    "subjects": [
      "Экономика",
      "Математика",
      "Обществознание",
      "Русский язык",
      "История"
    ],
    "benefits": {
      "bvi": false,
      "points100": false,
      "additionalPoints": 0,
      "grants": null,
      "tuitionDiscount": null,
      "priority": false,
      "earlyAdmission": false
    },
    "relevantDirections": [
      "экономика",
      "бизнес"
    ],
    "dates": {
      "registration": "2025-04-01 - 2025-09-15",
      "event": "2025-09-21 - 2026-05-31",
      "final": "2026-05-31"
    },
    "cost": {
      "type": "бесплатно",
      "amount": 0
    },
    "participationRequirements": [
      "Окончание 9 класса",
      "Результаты вступительных испытаний ЭМШ"
    ],
    "selectionProcess": "Вступительные испытания ЭМШ (тесты по математике и общеобразовательному предмету + собеседование)",
    "participantLimit": 50,
    "website": "https://emsch.ru",
    "regulations": null
  }
]